{"is_source_file": false, "format": "", "description": "", "external_files": [], "external_methods": [], "published": [], "classes": [], "methods": [], "calls": [], "search-terms": ["CSS", "tic-tac-toe", "responsive", "CSS variables", "grid layout", "UI styling", "frontend styles", "App.css"], "state": 2, "file_id": 13, "knowledge_revision": 28, "git_revision": "894d7289d0f8e0d968fb0ce9b3c24fc0081568a9", "hash": "3a389dc2a110e4d0c236115b20bade4d", "format-version": 4, "code-base-name": "tic_tac_toe_frontend", "filename": "tic_tac_toe_frontend/src/App.css", "revision_history": [{"28": "894d7289d0f8e0d968fb0ce9b3c24fc0081568a9"}]}